{
  "NumberOfTasks": 75,
  "NumberOfWorkers": 11,
  "NumberOfPeriods": 2,
  "OriginalMaximumMeanCycleTime": 47,
  "MaximumMeanCycleTime": 70,
  "PercentageAppliedOverOriginalMaximumMeanCycleTime": 1.5,
  "MeanCycleTime": 66.22727272727273,
  "ExecutionTimeMs": 710469,
  "OF": 150,
  "Assignment": {
    "Period 0": {
      "Station 0": {
        "Worker 0": [
          0,
          2,
          5,
          12
        ]
      },
      "Station 1": {
        "Worker 3": [
          3,
          4,
          8
        ]
      },
      "Station 10": {
        "Worker 1": [
          29,
          40,
          50,
          62,
          63,
          66,
          71
        ]
      },
      "Station 2": {
        "Worker 8": [
          1,
          6,
          10,
          14,
          19,
          23,
          24,
          27
        ]
      },
      "Station 3": {
        "Worker 6": [
          13,
          26,
          33,
          34
        ]
      },
      "Station 4": {
        "Worker 9": [
          7,
          16,
          41,
          46,
          48,
          58,
          65,
          67,
          73
        ]
      },
      "Station 5": {
        "Worker 10": [
          9,
          11,
          15,
          18,
          20,
          32,
          35,
          39,
          42,
          49
        ]
      },
      "Station 6": {
        "Worker 2": [
          17,
          25,
          45,
          51,
          53,
          68
        ]
      },
      "Station 7": {
        "Worker 7": [
          31,
          43,
          47,
          72
        ]
      },
      "Station 8": {
        "Worker 5": [
          21,
          28,
          30,
          36,
          37,
          52,
          54,
          55,
          56,
          57,
          60,
          74
        ]
      },
      "Station 9": {
        "Worker 4": [
          22,
          38,
          44,
          59,
          61,
          64,
          69,
          70
        ]
      }
    },
    "Period 1": {
      "Station 0": {
        "Worker 1": [
          0,
          5,
          9
        ]
      },
      "Station 1": {
        "Worker 6": [
          1,
          2,
          3,
          4,
          11,
          18
        ]
      },
      "Station 10": {
        "Worker 7": [
          22,
          53,
          62,
          66,
          68,
          74
        ]
      },
      "Station 2": {
        "Worker 5": [
          6,
          8,
          14,
          17,
          19
        ]
      },
      "Station 3": {
        "Worker 9": [
          13,
          23,
          26,
          35,
          39,
          42
        ]
      },
      "Station 4": {
        "Worker 4": [
          10,
          12,
          15,
          20,
          24,
          28,
          33,
          34,
          41,
          46,
          48,
          49,
          54,
          60
        ]
      },
      "Station 5": {
        "Worker 10": [
          25,
          30,
          31,
          45,
          51,
          55
        ]
      },
      "Station 6": {
        "Worker 3": [
          7,
          16,
          27,
          58,
          63,
          65,
          67,
          69,
          71
        ]
      },
      "Station 7": {
        "Worker 8": [
          21,
          32,
          37,
          43,
          44,
          52,
          57,
          61,
          72
        ]
      },
      "Station 8": {
        "Worker 2": [
          36,
          38,
          40,
          47,
          56,
          64,
          70,
          73
        ]
      },
      "Station 9": {
        "Worker 0": [
          29,
          50,
          59
        ]
      }
    }
  },
  "NewTasksExecutedByWorkerOnEachPeriod": {
    "Period 0": {
      "Worker 0": [
        0,
        2,
        5,
        12
      ],
      "Worker 1": [
        29,
        40,
        50,
        62,
        63,
        66,
        71
      ],
      "Worker 10": [
        9,
        11,
        15,
        18,
        20,
        32,
        35,
        39,
        42,
        49
      ],
      "Worker 2": [
        17,
        25,
        45,
        51,
        53,
        68
      ],
      "Worker 3": [
        3,
        4,
        8
      ],
      "Worker 4": [
        22,
        38,
        44,
        59,
        61,
        64,
        69,
        70
      ],
      "Worker 5": [
        21,
        28,
        30,
        36,
        37,
        52,
        54,
        55,
        56,
        57,
        60,
        74
      ],
      "Worker 6": [
        13,
        26,
        33,
        34
      ],
      "Worker 7": [
        31,
        43,
        47,
        72
      ],
      "Worker 8": [
        1,
        6,
        10,
        14,
        19,
        23,
        24,
        27
      ],
      "Worker 9": [
        7,
        16,
        41,
        46,
        48,
        58,
        65,
        67,
        73
      ]
    },
    "Period 1": {
      "Worker 0": [
        29,
        50,
        59
      ],
      "Worker 1": [
        0,
        5,
        9
      ],
      "Worker 10": [
        25,
        30,
        31,
        45,
        51,
        55
      ],
      "Worker 2": [
        36,
        38,
        40,
        47,
        56,
        64,
        70,
        73
      ],
      "Worker 3": [
        7,
        16,
        27,
        58,
        63,
        65,
        67,
        69,
        71
      ],
      "Worker 4": [
        10,
        12,
        15,
        20,
        24,
        28,
        33,
        34,
        41,
        46,
        48,
        49,
        54,
        60
      ],
      "Worker 5": [
        6,
        8,
        14,
        17,
        19
      ],
      "Worker 6": [
        1,
        2,
        3,
        4,
        11,
        18
      ],
      "Worker 7": [
        22,
        53,
        62,
        66,
        68,
        74
      ],
      "Worker 8": [
        21,
        32,
        37,
        43,
        44,
        52,
        57,
        61,
        72
      ],
      "Worker 9": [
        13,
        23,
        26,
        35,
        39,
        42
      ]
    }
  }
}