{
  "NumberOfTasks": 25,
  "NumberOfWorkers": 4,
  "NumberOfPeriods": 2,
  "OriginalMaximumMeanCycleTime": 27,
  "MaximumMeanCycleTime": 29,
  "PercentageAppliedOverOriginalMaximumMeanCycleTime": 1.1,
  "MeanCycleTime": 19.75,
  "ExecutionTimeMs": 3006,
  "OF": 27,
  "Assignment": {
    "Period 0": {
      "Station 0": {
        "Worker 3": [
          0,
          1,
          2,
          3,
          4,
          5
        ]
      },
      "Station 1": {
        "Worker 1": [
          6,
          7,
          8,
          11,
          14
        ]
      },
      "Station 2": {
        "Worker 0": [
          9,
          10,
          12,
          13,
          16,
          18,
          22
        ]
      },
      "Station 3": {
        "Worker 2": [
          15,
          17,
          19,
          20,
          21,
          23,
          24
        ]
      }
    },
    "Period 1": {
      "Station 0": {
        "Worker 3": [
          0,
          1,
          2,
          3,
          4,
          5
        ]
      },
      "Station 1": {
        "Worker 1": [
          6,
          7,
          8,
          11,
          14
        ]
      },
      "Station 2": {
        "Worker 0": [
          10,
          12,
          13,
          16,
          22
        ]
      },
      "Station 3": {
        "Worker 2": [
          9,
          15,
          17,
          18,
          19,
          20,
          21,
          23,
          24
        ]
      }
    }
  },
  "NewTasksExecutedByWorkerOnEachPeriod": {
    "Period 0": {
      "Worker 0": [
        9,
        10,
        12,
        13,
        16,
        18,
        22
      ],
      "Worker 1": [
        6,
        7,
        8,
        11,
        14
      ],
      "Worker 2": [
        15,
        17,
        19,
        20,
        21,
        23,
        24
      ],
      "Worker 3": [
        0,
        1,
        2,
        3,
        4,
        5
      ]
    },
    "Period 1": {
      "Worker 0": [],
      "Worker 1": [],
      "Worker 2": [
        9,
        18
      ],
      "Worker 3": []
    }
  }
}