{
  "NumberOfTasks": 25,
  "NumberOfWorkers": 6,
  "NumberOfPeriods": 2,
  "OriginalMaximumMeanCycleTime": 16,
  "MaximumMeanCycleTime": 20,
  "PercentageAppliedOverOriginalMaximumMeanCycleTime": 1.25,
  "MeanCycleTime": 17.416666666666668,
  "ExecutionTimeMs": 4178,
  "OF": 50,
  "Assignment": {
    "Period 0": {
      "Station 0": {
        "Worker 4": [
          0,
          1,
          2
        ]
      },
      "Station 1": {
        "Worker 0": [
          3,
          4,
          5
        ]
      },
      "Station 2": {
        "Worker 3": [
          6,
          7,
          8,
          10,
          11
        ]
      },
      "Station 3": {
        "Worker 5": [
          12,
          13,
          18,
          19
        ]
      },
      "Station 4": {
        "Worker 1": [
          15,
          20,
          23
        ]
      },
      "Station 5": {
        "Worker 2": [
          9,
          14,
          16,
          17,
          21,
          22,
          24
        ]
      }
    },
    "Period 1": {
      "Station 0": {
        "Worker 5": [
          0,
          1
        ]
      },
      "Station 1": {
        "Worker 1": [
          2,
          3,
          4
        ]
      },
      "Station 2": {
        "Worker 2": [
          5,
          6,
          7,
          8,
          11
        ]
      },
      "Station 3": {
        "Worker 4": [
          9,
          10,
          12,
          13,
          14,
          16
        ]
      },
      "Station 4": {
        "Worker 3": [
          15,
          18,
          19,
          20,
          23
        ]
      },
      "Station 5": {
        "Worker 0": [
          17,
          21,
          22,
          24
        ]
      }
    }
  },
  "NewTasksExecutedByWorkerOnEachPeriod": {
    "Period 0": {
      "Worker 0": [
        3,
        4,
        5
      ],
      "Worker 1": [
        15,
        20,
        23
      ],
      "Worker 2": [
        9,
        14,
        16,
        17,
        21,
        22,
        24
      ],
      "Worker 3": [
        6,
        7,
        8,
        10,
        11
      ],
      "Worker 4": [
        0,
        1,
        2
      ],
      "Worker 5": [
        12,
        13,
        18,
        19
      ]
    },
    "Period 1": {
      "Worker 0": [
        17,
        21,
        22,
        24
      ],
      "Worker 1": [
        2,
        3,
        4
      ],
      "Worker 2": [
        5,
        6,
        7,
        8,
        11
      ],
      "Worker 3": [
        15,
        18,
        19,
        20,
        23
      ],
      "Worker 4": [
        9,
        10,
        12,
        13,
        14,
        16
      ],
      "Worker 5": [
        0,
        1
      ]
    }
  }
}