{
  "NumberOfTasks": 25,
  "NumberOfWorkers": 4,
  "NumberOfPeriods": 2,
  "OriginalMaximumMeanCycleTime": 28,
  "MaximumMeanCycleTime": 35,
  "PercentageAppliedOverOriginalMaximumMeanCycleTime": 1.25,
  "MeanCycleTime": 31.25,
  "ExecutionTimeMs": 273,
  "OF": 50,
  "Assignment": {
    "Period 0": {
      "Station 0": {
        "Worker 1": [
          0,
          1,
          2,
          3,
          4,
          5
        ]
      },
      "Station 1": {
        "Worker 3": [
          6,
          7,
          8,
          9,
          10,
          11,
          14
        ]
      },
      "Station 2": {
        "Worker 2": [
          12,
          13,
          15,
          16,
          19,
          22
        ]
      },
      "Station 3": {
        "Worker 0": [
          17,
          18,
          20,
          21,
          23,
          24
        ]
      }
    },
    "Period 1": {
      "Station 0": {
        "Worker 2": [
          0,
          1,
          2,
          3,
          4,
          5
        ]
      },
      "Station 1": {
        "Worker 0": [
          6,
          7,
          8,
          10,
          11,
          14
        ]
      },
      "Station 2": {
        "Worker 3": [
          12,
          13,
          15,
          18,
          19,
          20,
          21,
          23
        ]
      },
      "Station 3": {
        "Worker 1": [
          9,
          16,
          17,
          22,
          24
        ]
      }
    }
  },
  "NewTasksExecutedByWorkerOnEachPeriod": {
    "Period 0": {
      "Worker 0": [
        17,
        18,
        20,
        21,
        23,
        24
      ],
      "Worker 1": [
        0,
        1,
        2,
        3,
        4,
        5
      ],
      "Worker 2": [
        12,
        13,
        15,
        16,
        19,
        22
      ],
      "Worker 3": [
        6,
        7,
        8,
        9,
        10,
        11,
        14
      ]
    },
    "Period 1": {
      "Worker 0": [
        6,
        7,
        8,
        10,
        11,
        14
      ],
      "Worker 1": [
        9,
        16,
        17,
        22,
        24
      ],
      "Worker 2": [
        0,
        1,
        2,
        3,
        4,
        5
      ],
      "Worker 3": [
        12,
        13,
        15,
        18,
        19,
        20,
        21,
        23
      ]
    }
  }
}